vendy/__init__.py
vendy/__main__.py
vendy/third_party/__init__.py
vendy/third_party/pip/__init__.py
vendy/third_party/pip/from_pip.py
vendy-0.0.3.dist-info/LICENSE
vendy-0.0.3.dist-info/METADATA
vendy-0.0.3.dist-info/WHEEL
vendy-0.0.3.dist-info/entry_points.txt
vendy-0.0.3.dist-info/top_level.txt
vendy-0.0.3.dist-info/RECORD
