Metadata-Version: 2.1
Name: vendy
Version: 0.0.3
Summary: Vendy is a tool for vendoring third-party packages into your project
Home-page: http://github.com/di/vendy
Author: Dustin Ingram
Author-email: di@python.org
Classifier: License :: OSI Approved :: Apache Software License
Classifier: Programming Language :: Python :: 3
Classifier: Programming Language :: Python :: 3.5
Classifier: Programming Language :: Python :: 3.6
Classifier: Programming Language :: Python :: 3.7
Requires-Python: >=2.7,!=3.0,!=3.1,!=3.2,!=3.3
License-File: LICENSE
Requires-Dist: click
Requires-Dist: requests
Requires-Dist: toml
